{
  "id": "dioscorea__yam_",
  "name": "Dioscorea (Yam)",
  "data": [
    {
      "date": null,
      "prices": []
    },
    {
      "date": "October 6, 2025",
      "prices": [
        {
          "place": "ALAPUZHA",
          "KERALA": {
            "wp": "80",
            "rp": "88"
          },
          "OUT_OF_STATE": {
            "wp": "0",
            "rp": "0"
          }
        }
      ]
    },
    {
      "date": "October 7, 2025",
      "prices": [
        {
          "place": "ALAPUZHA",
          "KERALA": {
            "wp": "80",
            "rp": "88"
          },
          "OUT_OF_STATE": {
            "wp": "0",
            "rp": "0"
          }
        }
      ]
    },
    {
      "date": "October 9, 2025",
      "prices": [
        {
          "place": "ALAPUZHA",
          "KERALA": {
            "wp": "80",
            "rp": "88"
          },
          "OUT_OF_STATE": {
            "wp": "0",
            "rp": "0"
          }
        }
      ]
    }
  ]
}